notiq/__init__.py
notiq/py.typed
notiq-0.0.1.dist-info/WHEEL
notiq-0.0.1.dist-info/METADATA
notiq-0.0.1.dist-info/RECORD
