Metadata-Version: 2.3
Name: notiq
Version: 0.0.1
Summary: Notification, analytics and job queue system. currently in planning phase
Author: HERITAGE-XION
Author-email: HERITAGE-XION <iheritage934@gmail.com>
Requires-Python: >=3.14
